ucommander/__init__.py
ucommander/__main__.py
ucommander/commander.py
ucommander-1.0.2.dist-info/LICENSE
ucommander-1.0.2.dist-info/METADATA
ucommander-1.0.2.dist-info/WHEEL
ucommander-1.0.2.dist-info/top_level.txt
ucommander-1.0.2.dist-info/RECORD
