Metadata-Version: 2.1
Name: ucommander
Version: 1.0.2
Summary: Interface with code running on a microprocessor via serial
Home-page: https://github.com/aeetos/ucommander-py
Author: Mark A Kendrick
Author-email: code@ikend.com
License: MIT
Platform: UNKNOWN
Classifier: Programming Language :: Python :: 3
Classifier: License :: OSI Approved :: MIT License
Classifier: Operating System :: OS Independent
Requires: pyserial
Requires-Python: >=3.4
Requires-Dist: pyserial (>=3.4)
